tstools/__init__.py
tstools/moments.py
tstools/vis.py
tstools_ieva-0.1.dist-info/METADATA
tstools_ieva-0.1.dist-info/WHEEL
tstools_ieva-0.1.dist-info/top_level.txt
tstools_ieva-0.1.dist-info/RECORD
